{
  "project_info": {
    "project_number": "598922521405",
    "project_id": "danielgutierreztorres-recall",
    "storage_bucket": "danielgutierreztorres-recall.firebasestorage.app"
  },
  "client": [
    {
      "client_info": {
        "mobilesdk_app_id": "1:598922521405:android:d1aee9db63b7b9dc3f7354",
        "android_client_info": {
          "package_name": "com.example.danelgutierreztorrespruebatecnica_app"
        }
      },
      "oauth_client": [],
      "api_key": [
        {
          "current_key": "AIzaSyC60RnpBSwen3shr0sFJX7T5jz5trgTC2o"
        }
      ],
      "services": {
        "appinvite_service": {
          "other_platform_oauth_client": []
        }
      }
    }
  ],
  "configuration_version": "1"
}